git_pip/__init__.py
git_pip/main.py
git_pip-0.1.0.dist-info/METADATA
git_pip-0.1.0.dist-info/WHEEL
git_pip-0.1.0.dist-info/entry_points.txt
git_pip-0.1.0.dist-info/top_level.txt
git_pip-0.1.0.dist-info/RECORD
