Metadata-Version: 2.1
Name: git-pip
Version: 0.1.0
Summary: A brief description of the git_pip package
Home-page: https://github.com/mantouRobot/git_pip
Author: mantou
Author-email: your.email@example.com
Classifier: Programming Language :: Python :: 3
Classifier: License :: OSI Approved :: MIT License
Classifier: Operating System :: OS Independent
Requires-Python: >=3.6
Requires-Dist: numpy
Requires-Dist: requests
